README.txt
failureaction.py
setup.py
failureaction.egg-info/PKG-INFO
failureaction.egg-info/SOURCES.txt
failureaction.egg-info/dependency_links.txt
failureaction.egg-info/top_level.txt
failureaction.egg-info/zip-safe