Metadata-Version: 1.0
Name: failureaction
Version: 1.0a1
Summary: Decorators for actions executed in case of an exception
Home-page: UNKNOWN
Author: Tom Gross
Author-email: itconsense@gmail.com
License: ZPL 2.1
Keywords: Exception Decorator Zope
Platform: UNKNOWN
Classifier: Development Status :: 3 - Alpha
Classifier: Intended Audience :: Developers
Classifier: License :: OSI Approved :: Zope Public License
Classifier: Topic :: Software Development :: Libraries :: Python Modules
